qtmodern6/__init__.py
qtmodern6/_utils.py
qtmodern6/styles.py
qtmodern6/windows.py
qtmodern6/resources/frameless.qss
qtmodern6/resources/style.qss
qtmodern6-0.1.0.dist-info/LICENSE
qtmodern6-0.1.0.dist-info/METADATA
qtmodern6-0.1.0.dist-info/WHEEL
qtmodern6-0.1.0.dist-info/top_level.txt
qtmodern6-0.1.0.dist-info/RECORD
