Metadata-Version: 2.1
Name: qtmodern6
Version: 0.1.0
Summary: PySide6 Widgets Modern User Interface
Home-page: https://www.github.com/hualayn/qtmodern6
Author: hua Layn
Author-email: layn@jinkuni.com
License: MIT
Classifier: Development Status :: 3 - Alpha
Classifier: Intended Audience :: Developers
Classifier: License :: OSI Approved :: MIT License
Classifier: Operating System :: OS Independent
Classifier: Programming Language :: Python
Classifier: Topic :: Software Development :: User Interfaces
License-File: LICENSE
Requires-Dist: PySide6>=6.0.0
